README.rst
setup.py
djmodel_filler/__init__.py
djmodel_filler/utils.py
djmodel_filler.egg-info/PKG-INFO
djmodel_filler.egg-info/SOURCES.txt
djmodel_filler.egg-info/dependency_links.txt
djmodel_filler.egg-info/not-zip-safe
djmodel_filler.egg-info/requires.txt
djmodel_filler.egg-info/top_level.txt