Metadata-Version: 1.0
Name: djmodel-filler
Version: 0.1.1
Summary: Django model fill utilite
Home-page: http://github.com/gebriallairbeg/djmodel_filler
Author: Pavel Sherepo
Author-email: pavel.sherepo@gmail.com
License: MIT
Platform: UNKNOWN
